click_loguru/__init__.py
click_loguru/decorators.py
click_loguru/intercept.py
click_loguru_decorators-0.1.0.dist-info/LICENSE
click_loguru_decorators-0.1.0.dist-info/METADATA
click_loguru_decorators-0.1.0.dist-info/WHEEL
click_loguru_decorators-0.1.0.dist-info/top_level.txt
click_loguru_decorators-0.1.0.dist-info/zip-safe
click_loguru_decorators-0.1.0.dist-info/RECORD
