Metadata-Version: 2.1
Name: click-loguru-decorators
Version: 0.1.0
Summary: Easy integration of Click and loguru
Home-page: https://github.com/illagrenan/click-loguru-decorators
Author: Vasek Dohnal
Author-email: vaclav.dohnal@gmail.com
License: MIT
Platform: UNKNOWN
Classifier: Development Status :: 3 - Alpha
Classifier: Intended Audience :: Developers
Classifier: License :: OSI Approved :: MIT License
Classifier: Natural Language :: English
Classifier: Programming Language :: Python :: 3.8
Classifier: Programming Language :: Python :: 3 :: Only
Classifier: Operating System :: OS Independent
Requires-Python: ~=3.8
Requires-Dist: loguru
Requires-Dist: Click
